relibmss-0.8.1.dist-info/METADATA
relibmss-0.8.1.dist-info/WHEEL
relibmss/bss.py
relibmss/mss.py
relibmss/__init__.py
relibmss/mdd.py
relibmss/bdd.py
relibmss/relibmss.cpython-39-aarch64-linux-gnu.so
relibmss-0.8.1.dist-info/RECORD
