Metadata-Version: 2.4
Name: relibmss
Version: 0.8.1
Summary: A Python package for binary/multi state systems
Home-Page: https://github.com/okamumu/relibmss
Author-email: Hiroyuki Okamura <okamu@hiroshima-u.ac.jp>
License: MIT
Project-URL: Source Code, https://github.com/okamumu/relibmss
